pythontemplatepackage/__init__.py
pythontemplatepackage/myclass.py
pythontemplatepackage/rename.py
pythontemplatepackage-0.0.6.dist-info/LICENSE
pythontemplatepackage-0.0.6.dist-info/METADATA
pythontemplatepackage-0.0.6.dist-info/WHEEL
pythontemplatepackage-0.0.6.dist-info/top_level.txt
pythontemplatepackage-0.0.6.dist-info/RECORD
