Metadata-Version: 2.1
Name: pythontemplatepackage
Version: 0.0.6
Summary: A template repo for Python packages with GitHub actions and documentation
Home-page: https://github.com/robert-lieck/pythontemplatepackage
Author: Robert Lieck
Author-email: robert.lieck@durham.ac.uk
Classifier: Programming Language :: Python :: 3
Classifier: License :: OSI Approved :: GNU General Public License v3 (GPLv3)
Classifier: Operating System :: OS Independent
Requires-Python: >=3.9
License-File: LICENSE
Requires-Dist: colorama
